skill_news/LICENSE.md
skill_news/README.md
skill_news/__init__.py
skill_news/skill.json
skill_news/version.py
skill_news/version_bump.py
skill_news/dialog/ca-es/OnlyNews.dialog
skill_news/dialog/ca-es/PlayTheNews.list
skill_news/dialog/ca-es/alt.feed.name.value
skill_news/dialog/ca-es/could.not.start.the.news.feed.dialog
skill_news/dialog/ca-es/news.dialog
skill_news/dialog/da-dk/alt.feed.name.value
skill_news/dialog/da-dk/could.not.start.the.news.feed.dialog
skill_news/dialog/da-dk/news.dialog
skill_news/dialog/de-de/OnlyNews.dialog
skill_news/dialog/de-de/PlayTheNews.list
skill_news/dialog/de-de/alt.feed.name.value
skill_news/dialog/de-de/could.not.start.the.news.feed.dialog
skill_news/dialog/de-de/country.default.value
skill_news/dialog/de-de/news.dialog
skill_news/dialog/el-gr/alt.feed.name.value
skill_news/dialog/el-gr/could.not.start.the.news.feed.dialog
skill_news/dialog/el-gr/country.default.value
skill_news/dialog/el-gr/news.dialog
skill_news/dialog/en-us/OnlyNews.dialog
skill_news/dialog/en-us/PlayTheNews.list
skill_news/dialog/en-us/alt.feed.name.value
skill_news/dialog/en-us/could.not.start.the.news.feed.dialog
skill_news/dialog/en-us/country.default.value
skill_news/dialog/en-us/news.dialog
skill_news/dialog/es-es/alt.feed.name.value
skill_news/dialog/es-es/could.not.start.the.news.feed.dialog
skill_news/dialog/es-es/country.default.value
skill_news/dialog/es-es/news.dialog
skill_news/dialog/fr-fr/OnlyNews.dialog
skill_news/dialog/fr-fr/PlayTheNews.list
skill_news/dialog/fr-fr/alt.feed.name.value
skill_news/dialog/fr-fr/could.not.start.the.news.feed.dialog
skill_news/dialog/fr-fr/country.default.value
skill_news/dialog/fr-fr/news.dialog
skill_news/dialog/gl-es/OnlyNews.dialog
skill_news/dialog/gl-es/PlayTheNews.list
skill_news/dialog/gl-es/alt.feed.name.value
skill_news/dialog/gl-es/could.not.start.the.news.feed.dialog
skill_news/dialog/gl-es/news.dialog
skill_news/dialog/hu-hu/news.dialog
skill_news/dialog/it-it/alt.feed.name.value
skill_news/neon_skill_news.egg-info/PKG-INFO
skill_news/neon_skill_news.egg-info/SOURCES.txt
skill_news/neon_skill_news.egg-info/dependency_links.txt
skill_news/neon_skill_news.egg-info/entry_points.txt
skill_news/neon_skill_news.egg-info/requires.txt
skill_news/neon_skill_news.egg-info/top_level.txt
neon_skill_news-0.0.1.dist-info/LICENSE.md
neon_skill_news-0.0.1.dist-info/METADATA
neon_skill_news-0.0.1.dist-info/WHEEL
neon_skill_news-0.0.1.dist-info/entry_points.txt
neon_skill_news-0.0.1.dist-info/top_level.txt
neon_skill_news-0.0.1.dist-info/RECORD
