Metadata-Version: 2.1
Name: neon-skill-news
Version: 0.0.1
Summary: UNKNOWN
Home-page: https://github.com/NeonGeckoCom/skill-news
Author: Neongecko
Author-email: developers@neon.ai
License: BSD-3-Clause
Platform: UNKNOWN
Requires-Dist: beautifulsoup4 (==4.9.0)
Requires-Dist: feedparser (~=6.0.0)
Requires-Dist: neon-utils (<2.0.0,>=0.6)
